aiida_workgraph_web_ui/__init__.py
aiida_workgraph_web_ui/backend/__init__.py
aiida_workgraph_web_ui/backend/cmd_web.py
aiida_workgraph_web_ui/backend/main.py
aiida_workgraph_web_ui/backend/app/__init__.py
aiida_workgraph_web_ui/backend/app/api.py
aiida_workgraph_web_ui/backend/app/daemon.py
aiida_workgraph_web_ui/backend/app/data_node.py
aiida_workgraph_web_ui/backend/app/group_node.py
aiida_workgraph_web_ui/backend/app/node_table.py
aiida_workgraph_web_ui/backend/app/process_node.py
aiida_workgraph_web_ui/backend/app/scheduler.py
aiida_workgraph_web_ui/backend/app/task.py
aiida_workgraph_web_ui/backend/app/utils.py
aiida_workgraph_web_ui/backend/app/workchain.py
aiida_workgraph_web_ui/backend/app/workgraph.py
aiida_workgraph_web_ui/frontend/.gitignore
aiida_workgraph_web_ui/frontend/.rete-patch
aiida_workgraph_web_ui/frontend/README.md
aiida_workgraph_web_ui/frontend/package-lock.json
aiida_workgraph_web_ui/frontend/package.json
aiida_workgraph_web_ui/frontend/tsconfig.json
aiida_workgraph_web_ui/frontend/build/asset-manifest.json
aiida_workgraph_web_ui/frontend/build/favicon.ico
aiida_workgraph_web_ui/frontend/build/index.html
aiida_workgraph_web_ui/frontend/build/manifest.json
aiida_workgraph_web_ui/frontend/build/robots.txt
aiida_workgraph_web_ui/frontend/build/static/css/main.8061ec00.css
aiida_workgraph_web_ui/frontend/build/static/css/main.8061ec00.css.map
aiida_workgraph_web_ui/frontend/build/static/js/787.095790c7.chunk.js
aiida_workgraph_web_ui/frontend/build/static/js/787.095790c7.chunk.js.map
aiida_workgraph_web_ui/frontend/build/static/js/main.6705cab4.js
aiida_workgraph_web_ui/frontend/build/static/js/main.6705cab4.js.LICENSE.txt
aiida_workgraph_web_ui/frontend/build/static/js/main.6705cab4.js.map
aiida_workgraph_web_ui/frontend/public/favicon.ico
aiida_workgraph_web_ui/frontend/public/index.html
aiida_workgraph_web_ui/frontend/public/manifest.json
aiida_workgraph_web_ui/frontend/public/robots.txt
aiida_workgraph_web_ui/frontend/src/App.css
aiida_workgraph_web_ui-0.1.4.dist-info/entry_points.txt
aiida_workgraph_web_ui-0.1.4.dist-info/licenses/LICENSE
aiida_workgraph_web_ui-0.1.4.dist-info/WHEEL
aiida_workgraph_web_ui-0.1.4.dist-info/METADATA
aiida_workgraph_web_ui-0.1.4.dist-info/RECORD
